[
  {
    "Región":"Asia",
    "Debajo de 15 años (proporción de población)":"24 %",
    "Sobre los 65 años (proporción de población)":"8 %"
  },
  {
    "Región":"África",
    "Debajo de 15 años (proporción de población)":"41 %",
    "Sobre los 65 años (proporción de población)":"3 %"
  },
  {
    "Región":"Europa",
    "Debajo de 15 años (proporción de población)":"16 %",
    "Sobre los 65 años (proporción de población)":"18 %"
  },
  {
    "Región":"Latinoamérica-Caribe",
    "Debajo de 15 años (proporción de población)":"26 %",
    "Sobre los 65 años (proporción de población)":"8 %"
  },
  {
    "Región":"EE. UU. y Canadá",
    "Debajo de 15 años (proporción de población)":"19 %",
    "Sobre los 65 años (proporción de población)":"15 %"
  },
  {
    "Región":"Oceanía",
    "Debajo de 15 años (proporción de población)":"23 %",
    "Sobre los 65 años (proporción de población)":"12 %"
  },
  {
    "Región":"Mundo",
    "Debajo de 15 años (proporción de población)":"26 %",
    "Sobre los 65 años (proporción de población)":"9 %"
  }
]